pages_cache
